dbt/adapters/sqlserver/__init__.py
dbt/adapters/sqlserver/__version__.py
dbt/adapters/sqlserver/sql_server_adapter.py
dbt/adapters/sqlserver/sql_server_column.py
dbt/adapters/sqlserver/sql_server_configs.py
dbt/adapters/sqlserver/sql_server_connection_manager.py
dbt/adapters/sqlserver/sql_server_credentials.py
dbt/include/sqlserver/__init__.py
dbt/include/sqlserver/dbt_project.yml
dbt/include/sqlserver/macros/adapters/columns.sql
dbt/include/sqlserver/macros/adapters/indexes.sql
dbt/include/sqlserver/macros/adapters/relation.sql
dbt/include/sqlserver/macros/materializations/models/table/clone.sql
dbt/include/sqlserver/macros/materializations/models/table/create_table_as.sql
dbt/include/sqlserver/macros/materializations/seeds/helpers.sql
dbt/include/sqlserver/macros/materializations/snapshots/snapshot.sql
dbt/include/sqlserver/macros/utils/split_part.sql
dbt/include/sqlserver/macros/utils/timestamps.sql
dbt_sqlserver_dyvenia-1.7.4.dist-info/LICENSE
dbt_sqlserver_dyvenia-1.7.4.dist-info/METADATA
dbt_sqlserver_dyvenia-1.7.4.dist-info/WHEEL
dbt_sqlserver_dyvenia-1.7.4.dist-info/top_level.txt
dbt_sqlserver_dyvenia-1.7.4.dist-info/RECORD
