Metadata-Version: 2.1
Name: dbt-sqlserver-dyvenia
Version: 1.7.4
Summary: A Microsoft SQL Server adapter plugin for dbt
Home-page: https://github.com/dbt-msft/dbt-sqlserver
Author: Mikael Ene, Anders Swanson, Sam Debruyn, Cor Zuurmond
License: MIT
Project-URL: Setup & configuration, https://docs.getdbt.com/reference/warehouse-profiles/mssql-profile
Project-URL: Documentation & usage, https://docs.getdbt.com/reference/resource-configs/mssql-configs
Project-URL: Changelog, https://github.com/dbt-msft/dbt-sqlserver/blob/master/CHANGELOG.md
Project-URL: Issue Tracker, https://github.com/dbt-msft/dbt-sqlserver/issues
Classifier: Development Status :: 5 - Production/Stable
Classifier: License :: OSI Approved :: MIT License
Classifier: Operating System :: Microsoft :: Windows
Classifier: Operating System :: MacOS :: MacOS X
Classifier: Operating System :: POSIX :: Linux
Classifier: Programming Language :: Python :: 3.7
Classifier: Programming Language :: Python :: 3.8
Classifier: Programming Language :: Python :: 3.9
Classifier: Programming Language :: Python :: 3.10
Classifier: Programming Language :: Python :: 3.11
License-File: LICENSE
Requires-Dist: dbt-core ~=1.7.2
Requires-Dist: dbt-fabric ~=1.7.2
Requires-Dist: pyodbc <5.1.0,>=4.0.35
Requires-Dist: azure-identity >=1.12.0
